partcsv/__init__.py
partcsv/core.py
partcsv/tests/test_init.py
partcsv-0.1.3.dist-info/LICENSE
partcsv-0.1.3.dist-info/WHEEL
partcsv-0.1.3.dist-info/METADATA
partcsv-0.1.3.dist-info/RECORD
